MANIFEST.in
README.rst
requirements.txt
setup.py
django_mbtiles.egg-info/PKG-INFO
django_mbtiles.egg-info/SOURCES.txt
django_mbtiles.egg-info/dependency_links.txt
django_mbtiles.egg-info/not-zip-safe
django_mbtiles.egg-info/requires.txt
django_mbtiles.egg-info/top_level.txt
mbtilesmap/__init__.py
mbtilesmap/models.py
mbtilesmap/tests.py
mbtilesmap/urls.py
mbtilesmap/utils.py
mbtilesmap/views.py
mbtilesmap/static/mbtilesmap/easey.handlers.js
mbtilesmap/static/mbtilesmap/easey.js
mbtilesmap/static/mbtilesmap/modestmaps.min.js
mbtilesmap/static/mbtilesmap/wax.mm.min.js
mbtilesmap/templates/mbtilesmap/head.html
mbtilesmap/templates/mbtilesmap/map.html
mbtilesmap/templatetags/__init__.py
mbtilesmap/templatetags/mbtilesmap_tags.py