Metadata-Version: 1.1
Name: django-mbtiles
Version: 1.3
Summary: Serve maps from MBTiles files using Django
Home-page: https://github.com/makinacorpus/django-mbtiles
Author: Mathieu Leplatre
Author-email: mathieu.leplatre@makina-corpus.com
License: UNKNOWN
Download-URL: http://pypi.python.org/pypi/django-mbtiles/
Platform: UNKNOWN
Classifier: Topic :: Utilities
Classifier: Natural Language :: English
Classifier: Operating System :: OS Independent
Classifier: Intended Audience :: Developers
Classifier: Environment :: Web Environment
Classifier: Framework :: Django
Classifier: Development Status :: 5 - Production/Stable
Classifier: Programming Language :: Python :: 2.5
